{"edges": [{"source": "HP:0000177", "target": "HP:0000288"}, {"source": "DDX59", "target": "HP:0000288"}, {"source": "HP:0001830", "target": "HP:0005817"}, {"source": "DDX59", "target": "HP:0001830"}, {"source": "DDX59", "target": "HP:0005817"}, {"source": "CSDE1", "target": "DDX59"}], "nodes": [{"id": "HP:0000177", "type": "HPO", "name": "Abnormal upper lip morphology", "cluster": "paris.cesna.2022:7205", "cluster_id": 649, "x": 0.9029646740499189, "y": -1.0}, {"id": "HP:0000288", "type": "HPO", "name": "Abnormality of the philtrum", "cluster": "paris.cesna.2022:7205", "cluster_id": 649, "x": 0.42375416451513, "y": -0.4841130232167739}, {"id": "DDX59", "type": "gene", "name": "DEAD-box helicase 59", "cluster": "paris.cesna.2022:7205", "cluster_id": 649, "x": -0.15452923101486513, "y": 0.1311522419483701}, {"id": "HP:0001830", "type": "HPO", "name": "Postaxial foot polydactyly", "cluster": "paris.cesna.2022:7205", "cluster_id": 649, "x": 0.04980198641168563, "y": 0.7977931869245029}, {"id": "HP:0005817", "type": "HPO", "name": "Postaxial polysyndactyly of foot", "cluster": "paris.cesna.2022:7205", "cluster_id": 649, "x": -0.4325223665294184, "y": 0.7751905719550796}, {"id": "CSDE1", "type": "gene", "name": "Cold shock domain containing E1", "cluster": "paris.cesna.2022:7205", "cluster_id": 649, "x": -0.7894692274324511, "y": -0.2200229776111789}], "hpoParentNodes": [{"id": "HP:0000159", "level": 1, "name": "Abnormal lip morphology", "type": "HPO Parent", "cluster": "paris.cesna.2022:7205", "cluster_id": 649}, {"id": "HP:0001829", "level": 1, "name": "Foot polydactyly", "type": "HPO Parent", "cluster": "paris.cesna.2022:7205", "cluster_id": 649}, {"id": "HP:0010322", "level": 1, "name": "Abnormality of the 5th toe", "type": "HPO Parent", "cluster": "paris.cesna.2022:7205", "cluster_id": 649}], "hpoParentEdges": [{"target": "HP:0000159", "source": "HP:0000177"}, {"target": "HP:0001829", "source": "HP:0001830"}, {"target": "HP:0001830", "source": "HP:0010322"}]}