{"edges": [{"source": "FAS", "target": "HP:0003493"}, {"source": "CD247", "target": "HP:0003493"}, {"source": "HP:0003493", "target": "MS4A1"}, {"source": "COPA", "target": "HP:0003493"}, {"source": "CTLA4", "target": "HP:0003493"}, {"source": "HP:0003493", "target": "PTPN22"}, {"source": "HP:0003493", "target": "RASGRP1"}, {"source": "HP:0003493", "target": "TREX1"}, {"source": "HP:0003493", "target": "IL2RA"}, {"source": "HP:0003493", "target": "IL2RB"}, {"source": "HP:0003493", "target": "MMP2"}, {"source": "HP:0003493", "target": "PLCG2"}, {"source": "HP:0003493", "target": "POU2AF1"}, {"source": "HP:0003493", "target": "LACC1"}, {"source": "HP:0003493", "target": "PTPN2"}, {"source": "ANKRD55", "target": "HP:0003493"}, {"source": "HP:0003493", "target": "SPIB"}, {"source": "HP:0003493", "target": "STAT4"}, {"source": "IL2RB", "target": "PTPN2"}, {"source": "CTLA4", "target": "PTPN2"}, {"source": "PTPN2", "target": "RASGRP1"}, {"source": "PLCG2", "target": "PTPN2"}, {"source": "ANKRD55", "target": "PTPN2"}, {"source": "CD247", "target": "PTPN2"}, {"source": "IL2RA", "target": "PTPN2"}, {"source": "PTPN2", "target": "PTPN22"}, {"source": "LACC1", "target": "PTPN2"}, {"source": "PTPN2", "target": "STAT4"}, {"source": "IL2RB", "target": "RASGRP1"}, {"source": "CTLA4", "target": "RASGRP1"}, {"source": "PLCG2", "target": "RASGRP1"}, {"source": "CD247", "target": "RASGRP1"}, {"source": "RASGRP1", "target": "STAT4"}, {"source": "PTPN22", "target": "RASGRP1"}, {"source": "IL2RA", "target": "RASGRP1"}, {"source": "FAS", "target": "IL2RB"}, {"source": "FAS", "target": "MMP2"}, {"source": "CTLA4", "target": "FAS"}, {"source": "FAS", "target": "STAT4"}, {"source": "CD247", "target": "FAS"}, {"source": "FAS", "target": "PLCG2"}, {"source": "FAS", "target": "PTPN22"}, {"source": "FAS", "target": "IL2RA"}, {"source": "FAS", "target": "POU2AF1"}, {"source": "FAS", "target": "MS4A1"}, {"source": "IL2RB", "target": "PLCG2"}, {"source": "CTLA4", "target": "PLCG2"}, {"source": "PLCG2", "target": "PTPN22"}, {"source": "CD247", "target": "PLCG2"}, {"source": "PLCG2", "target": "POU2AF1"}, {"source": "LACC1", "target": "PLCG2"}, {"source": "MS4A1", "target": "PLCG2"}, {"source": "LACC1", "target": "PTPN22"}, {"source": "MMP2", "target": "STAT4"}, {"source": "MMP2", "target": "SPIB"}, {"source": "CTLA4", "target": "MMP2"}, {"source": "CTLA4", "target": "IL2RB"}, {"source": "CTLA4", "target": "MS4A1"}, {"source": "ANKRD55", "target": "CTLA4"}, {"source": "CTLA4", "target": "IL2RA"}, {"source": "CTLA4", "target": "PTPN22"}, {"source": "CTLA4", "target": "STAT4"}, {"source": "CTLA4", "target": "POU2AF1"}, {"source": "CTLA4", "target": "SPIB"}, {"source": "CD247", "target": "CTLA4"}, {"source": "IL2RB", "target": "STAT4"}, {"source": "ANKRD55", "target": "STAT4"}, {"source": "PTPN22", "target": "STAT4"}, {"source": "CD247", "target": "STAT4"}, {"source": "IL2RA", "target": "STAT4"}, {"source": "SPIB", "target": "STAT4"}, {"source": "POU2AF1", "target": "STAT4"}, {"source": "IL2RB", "target": "PTPN22"}, {"source": "ANKRD55", "target": "PTPN22"}, {"source": "CD247", "target": "PTPN22"}, {"source": "IL2RA", "target": "PTPN22"}, {"source": "POU2AF1", "target": "PTPN22"}, {"source": "MS4A1", "target": "PTPN22"}, {"source": "IL2RA", "target": "IL2RB"}, {"source": "ANKRD55", "target": "IL2RA"}, {"source": "CD247", "target": "IL2RA"}, {"source": "IL2RA", "target": "SPIB"}, {"source": "IL2RA", "target": "MS4A1"}, {"source": "IL2RA", "target": "POU2AF1"}, {"source": "IL2RB", "target": "POU2AF1"}, {"source": "ANKRD55", "target": "IL2RB"}, {"source": "IL2RB", "target": "MS4A1"}, {"source": "CD247", "target": "IL2RB"}, {"source": "IL2RB", "target": "SPIB"}, {"source": "POU2AF1", "target": "SPIB"}, {"source": "MS4A1", "target": "POU2AF1"}, {"source": "CD247", "target": "MS4A1"}, {"source": "MS4A1", "target": "SPIB"}], "nodes": [{"id": "FAS", "name": "FAS", "cluster": "paris.cesna.2021:2795", "cluster_id": 1152, "x": 0.2056548050939907, "y": -0.3340371352132047}, {"id": "HP:0003493", "name": "HP:0003493", "cluster": "paris.cesna.2021:2795", "cluster_id": 1152, "x": 0.05638720968993452, "y": 0.1650019499547932}, {"id": "CD247", "name": "CD247", "cluster": "paris.cesna.2021:2795", "cluster_id": 1152, "x": -0.18351403191884635, "y": -0.386864246252331}, {"id": "MS4A1", "name": "MS4A1", "cluster": "paris.cesna.2021:2795", "cluster_id": 1152, "x": 0.2425302675113145, "y": -0.1321498523812144}, {"id": "COPA", "name": "COPA", "cluster": "paris.cesna.2021:2795", "cluster_id": 1152, "x": 0.08989690897944891, "y": 1.0}, {"id": "CTLA4", "name": "CTLA4", "cluster": "paris.cesna.2021:2795", "cluster_id": 1152, "x": 0.07715093109420919, "y": -0.031921212680888135}, {"id": "PTPN22", "name": "PTPN22", "cluster": "paris.cesna.2021:2795", "cluster_id": 1152, "x": -0.21034333987004306, "y": 0.002722630771377127}, {"id": "RASGRP1", "name": "RASGRP1", "cluster": "paris.cesna.2021:2795", "cluster_id": 1152, "x": -0.41802414509827907, "y": -0.2806387586175641}, {"id": "TREX1", "name": "TREX1", "cluster": "paris.cesna.2021:2795", "cluster_id": 1152, "x": 0.6125460486868554, "y": 0.7833331844274126}, {"id": "IL2RA", "name": "IL2RA", "cluster": "paris.cesna.2021:2795", "cluster_id": 1152, "x": -0.06516696855103297, "y": -0.08363095487407833}, {"id": "IL2RB", "name": "IL2RB", "cluster": "paris.cesna.2021:2795", "cluster_id": 1152, "x": -0.0957327769263896, "y": -0.24544570817105746}, {"id": "MMP2", "name": "MMP2", "cluster": "paris.cesna.2021:2795", "cluster_id": 1152, "x": 0.5952545000858699, "y": -0.03281600254060807}, {"id": "PLCG2", "name": "PLCG2", "cluster": "paris.cesna.2021:2795", "cluster_id": 1152, "x": -0.30200242117906695, "y": -0.16414071773374286}, {"id": "POU2AF1", "name": "POU2AF1", "cluster": "paris.cesna.2021:2795", "cluster_id": 1152, "x": 0.07245110403705826, "y": -0.44629953038446857}, {"id": "LACC1", "name": "LACC1", "cluster": "paris.cesna.2021:2795", "cluster_id": 1152, "x": -0.6024041852703856, "y": 0.3026687647904751}, {"id": "PTPN2", "name": "PTPN2", "cluster": "paris.cesna.2021:2795", "cluster_id": 1152, "x": -0.40509354864242114, "y": 0.03696927472523914}, {"id": "ANKRD55", "name": "ANKRD55", "cluster": "paris.cesna.2021:2795", "cluster_id": 1152, "x": -0.17023526992018873, "y": 0.2996852534612135}, {"id": "SPIB", "name": "SPIB", "cluster": "paris.cesna.2021:2795", "cluster_id": 1152, "x": 0.43127694663981797, "y": -0.2638304180904532}, {"id": "STAT4", "name": "STAT4", "cluster": "paris.cesna.2021:2795", "cluster_id": 1152, "x": 0.06936796555815432, "y": -0.1886065211909004}]}