{"edges": [["HP:0011971", "POU2AF1"], ["HP:0011971", "MMEL1"], ["HP:0011971", "SPIB"], ["FCGRT", "FCRL4"], ["CD40LG", "FCGRT"], ["FCGRT", "TNFSF13"], ["FCGRT", "IGJ"], ["FAIM3", "FCGRT"], ["FCER2", "FCGRT"], ["FCGRT", "SERPINB1"], ["FCER1G", "FCGRT"], ["CDR2", "FCGRT"], ["FCGRT", "IGHV4-38-2"], ["FCGRT", "GP6"], ["CDR1", "FCGRT"], ["CCRL2", "FCGRT"], ["FCGRT", "FCRLA"], ["FCGRT", "PRDM1"], ["CD40", "FCGRT"], ["FCGRT", "TNFSF13B"], ["CXCR5", "MMEL1"], ["CCRL2", "MMEL1"], ["FCRL3", "MMEL1"], ["MMEL1", "PRDM1"], ["CD40", "MMEL1"], ["MMEL1", "SPIB"], ["IGHV4-38-2", "MMEL1"], ["AICDA", "SERPINB1"], ["FCER2", "SERPINB1"], ["FCER1G", "SERPINB1"], ["CXCR5", "SERPINB1"], ["CD5", "SERPINB1"], ["SERPINB1", "TNFSF13"], ["CD40LG", "SERPINB1"], ["CD40", "SERPINB1"], ["SERPINB1", "TNFSF13B"], ["CSF2RA", "SERPINB1"], ["AICDA", "CDR1"], ["CDR1", "IGJ"], ["CDR1", "CDR2"], ["CDR1", "FCRL4"], ["CD5", "CDR1"], ["CDR1", "IGHV4-38-2"], ["CDR1", "IGLL5"], ["CDR1", "IGHV3-11"], ["CD40", "CDR1"], ["CDR1", "TNFSF13B"], ["CDR1", "IGHV3-15"], ["CD40LG", "CDR1"], ["AICDA", "CDR2"], ["CDR2", "IGJ"], ["CDR2", "IGHV4-38-2"], ["CDR2", "IGLL5"], ["CD40", "CDR2"], ["CD40LG", "CDR2"], ["CDR2", "FCRL4"], ["CDR2", "IGHV3-11"], ["CDR2", "TNFSF13B"], ["CD5", "CDR2"], ["CDR2", "IGHV3-15"], ["CDR2", "IGHV3-43D"], ["AICDA", "FCER2"], ["FCER2", "IGJ"], ["CD40LG", "FCER2"], ["FCER2", "FCRL4"], ["FCER2", "FCRL3"], ["FCER2", "IGLL5"], ["FCER2", "ZNF77"], ["FCER2", "IGHV4-38-2"], ["FCER2", "FCRLA"], ["CCRL2", "FCER2"], ["CD40", "FCER2"], ["FCER2", "SPIB"], ["FAIM3", "FCER2"], ["FCER1G", "FCER2"], ["FCER2", "POU2AF1"], ["CXCR5", "FCER2"], ["CD5", "FCER2"], ["FCER2", "TNFSF13B"], ["FCER2", "PRDM1"], ["AICDA", "TNFSF13B"], ["IGJ", "TNFSF13B"], ["FCRL4", "TNFSF13B"], ["FCER1G", "TNFSF13B"], ["CXCR5", "TNFSF13B"], ["GP6", "TNFSF13B"], ["CD5", "TNFSF13B"], ["TNFSF13", "TNFSF13B"], ["CCRL2", "TNFSF13B"], ["FCRLA", "TNFSF13B"], ["FCRL3", "TNFSF13B"], ["PRDM1", "TNFSF13B"], ["CD40LG", "TNFSF13B"], ["CD40", "TNFSF13B"], ["IGHV4-38-2", "TNFSF13B"], ["IGLL5", "TNFSF13B"], ["CSF2RA", "TNFSF13B"], ["POU2AF1", "TNFSF13B"], ["IGHV3-11", "TNFSF13B"], ["SPIB", "TNFSF13B"], ["AICDA", "CXCR5"], ["CXCR5", "IGJ"], ["CXCR5", "FCRL4"], ["CXCR5", "FCRLA"], ["CCRL2", "CXCR5"], ["CD40", "CXCR5"], ["CXCR5", "IGLL5"], ["CXCR5", "IGHV4-38-2"], ["CD40LG", "CXCR5"], ["CXCR5", "FCRL3"], ["CXCR5", "TNFSF13"], ["CD5", "CXCR5"], ["CXCR5", "PRDM1"], ["CXCR5", "POU2AF1"], ["CXCR5", "FAIM3"], ["CXCR5", "SPIB"], ["AICDA", "CD40LG"], ["CD40LG", "IGJ"], ["CD40LG", "FCRL4"], ["CD40LG", "FCER1G"], ["CD40LG", "GP6"], ["CD40LG", "CD5"], ["CD40LG", "TNFSF13"], ["CCRL2", "CD40LG"], ["CD40LG", "FCRLA"], ["CD40LG", "FCRL3"], ["CD40LG", "PRDM1"], ["CD40LG", "POU2AF1"], ["CD40LG", "SPIB"], ["CD40LG", "CSF2RA"], ["CD40", "CD40LG"], ["CD40LG", "IGLL5"], ["CD40LG", "IGHV4-38-2"], ["AICDA", "CD40"], ["CD40", "IGJ"], ["CD40", "FCRL4"], ["CD40", "FCER1G"], ["CD40", "GP6"], ["CD40", "CD5"], ["CD40", "TNFSF13"], ["CCRL2", "CD40"], ["CD40", "FCRLA"], ["CD40", "FCRL3"], ["CD40", "PRDM1"], ["CD40", "IGLL5"], ["CD40", "IGHV4-38-2"], ["CD40", "CSF2RA"], ["CD40", "SPIB"], ["CD40", "IGHV3-11"], ["CD40", "POU2AF1"], ["AICDA", "CCRL2"], ["CCRL2", "IGJ"], ["CCRL2", "FCRL4"], ["CCRL2", "FCER1G"], ["CCRL2", "CD5"], ["CCRL2", "TNFSF13"], ["CCRL2", "FCRL3"], ["CCRL2", "FCRLA"], ["CCRL2", "CSF2RA"], ["CCRL2", "IGHV4-38-2"], ["CCRL2", "FAIM3"], ["CCRL2", "SPIB"], ["CCRL2", "PRDM1"], ["CCRL2", "POU2AF1"], ["AICDA", "IGJ"], ["FCRL3", "IGJ"], ["FCRL4", "IGJ"], ["IGHV3-15", "IGJ"], ["IGJ", "SPIB"], ["IGJ", "TNFSF13"], ["FAIM3", "IGJ"], ["IGHV3-43D", "IGJ"], ["IGHV3-11", "IGJ"], ["FCER1G", "IGJ"], ["IGJ", "IGLL5"], ["IGJ", "POU2AF1"], ["IGHV4-38-2", "IGJ"], ["FCRLA", "IGJ"], ["IGJ", "LIME1"], ["CD5", "IGJ"], ["IGJ", "PRDM1"], ["AICDA", "PRDM1"], ["FCRL4", "PRDM1"], ["FCER1G", "PRDM1"], ["CD5", "PRDM1"], ["FCRLA", "PRDM1"], ["PRDM1", "SPIB"], ["POU2AF1", "PRDM1"], ["IGLL5", "PRDM1"], ["IGHV4-38-2", "PRDM1"], ["FCER1G", "GP6"], ["GP6", "TNFSF13"], ["CSF2RA", "FCER1G"], ["FCER1G", "FCRLA"], ["FCER1G", "IGHV4-38-2"], ["FCER1G", "IGLL5"], ["FCER1G", "TNFSF13"], ["FCER1G", "FCRL3"], ["CD5", "FCER1G"], ["FCER1G", "IGHV3-11"], ["AICDA", "POU2AF1"], ["FCRL4", "POU2AF1"], ["CD5", "POU2AF1"], ["FAIM3", "POU2AF1"], ["FCRLA", "POU2AF1"], ["FCRL3", "POU2AF1"], ["POU2AF1", "SPIB"], ["IGHV4-38-2", "POU2AF1"], ["IGLL5", "POU2AF1"], ["AICDA", "IGLL5"], ["FCRL4", "IGLL5"], ["IGLL5", "LIME1"], ["IGLL5", "ZNF77"], ["CD5", "IGLL5"], ["FCRLA", "IGLL5"], ["IGHV4-38-2", "IGLL5"], ["IGHV3-11", "IGLL5"], ["IGHV3-15", "IGLL5"], ["IGLL5", "SPIB"], ["IGHV3-43D", "IGLL5"], ["AICDA", "IGHV4-38-2"], ["FCRL4", "IGHV4-38-2"], ["IGHV4-38-2", "LIME1"], ["CD5", "IGHV4-38-2"], ["IGHV4-38-2", "TNFSF13"], ["FAIM3", "IGHV4-38-2"], ["FCRLA", "IGHV4-38-2"], ["FCRL3", "IGHV4-38-2"], ["IGHV4-38-2", "SPIB"], ["IGHV3-43D", "IGHV4-38-2"], ["IGHV3-15", "IGHV4-38-2"], ["IGHV3-11", "IGHV4-38-2"], ["AICDA", "SPIB"], ["FCRL4", "SPIB"], ["CD5", "SPIB"], ["FAIM3", "SPIB"], ["FCRLA", "SPIB"], ["FCRL3", "SPIB"], ["CSF2RA", "SPIB"], ["AICDA", "TNFSF13"], ["AICDA", "FCRL4"], ["AICDA", "IGHV3-11"], ["AICDA", "CD5"], ["CD5", "FCRL4"], ["CD5", "FCRLA"], ["CD5", "CSF2RA"], ["CD5", "FCRL3"], ["CD5", "TNFSF13"], ["CD5", "FAIM3"], ["IGHV3-15", "TNFSF13"], ["CSF2RA", "TNFSF13"], ["IGHV3-11", "ZNF77"], ["IGHV3-15", "ZNF77"], ["FCRL4", "IGHV3-11"], ["IGHV3-11", "LIME1"], ["FCRLA", "IGHV3-11"], ["IGHV3-11", "IGHV3-15"], ["IGHV3-11", "IGHV3-43D"], ["FAIM3", "FCRL4"], ["FAIM3", "FCRLA"], ["FAIM3", "FCRL3"], ["FCRL4", "FCRLA"], ["FCRL3", "FCRLA"], ["FCRL3", "FCRL4"], ["IGHV3-43D", "LIME1"], ["IGHV3-15", "LIME1"], ["IGHV3-15", "IGHV3-43D"]], "nodes": [{"id": "HP:0011971", "name": "HP:0011971", "cluster": "paris.infomap.2021:1738", "cluster_id": 758, "x": 0.25489733837305584, "y": 1.0}, {"id": "POU2AF1", "name": "POU2AF1", "cluster": "paris.infomap.2021:1738", "cluster_id": 758, "x": 0.14999099715194175, "y": 0.36227632697921053}, {"id": "MMEL1", "name": "MMEL1", "cluster": "paris.infomap.2021:1738", "cluster_id": 758, "x": 0.15793413691321048, "y": 0.6331751519547965}, {"id": "SPIB", "name": "SPIB", "cluster": "paris.infomap.2021:1738", "cluster_id": 758, "x": 0.06274843415844433, "y": 0.3712927192111529}, {"id": "FCGRT", "name": "FCGRT", "cluster": "paris.infomap.2021:1738", "cluster_id": 758, "x": 0.1161099182829988, "y": -0.3095870378473934}, {"id": "FCRL4", "name": "FCRL4", "cluster": "paris.infomap.2021:1738", "cluster_id": 758, "x": -0.15240480181900265, "y": 0.15621976182620453}, {"id": "CD40LG", "name": "CD40LG", "cluster": "paris.infomap.2021:1738", "cluster_id": 758, "x": 0.1464606213105579, "y": -0.10209440017878274}, {"id": "TNFSF13", "name": "TNFSF13", "cluster": "paris.infomap.2021:1738", "cluster_id": 758, "x": 0.2990137973766657, "y": -0.2689524720235387}, {"id": "IGJ", "name": "IGJ", "cluster": "paris.infomap.2021:1738", "cluster_id": 758, "x": -0.17146675710284587, "y": -0.0534395718098941}, {"id": "FAIM3", "name": "FAIM3", "cluster": "paris.infomap.2021:1738", "cluster_id": 758, "x": -0.088516423588708, "y": 0.02232251380207174}, {"id": "FCER2", "name": "FCER2", "cluster": "paris.infomap.2021:1738", "cluster_id": 758, "x": -0.0121793574567716, "y": -0.1249487586820898}, {"id": "SERPINB1", "name": "SERPINB1", "cluster": "paris.infomap.2021:1738", "cluster_id": 758, "x": 0.5109518970965284, "y": -0.13252334420725803}, {"id": "FCER1G", "name": "FCER1G", "cluster": "paris.infomap.2021:1738", "cluster_id": 758, "x": 0.21646235820598303, "y": -0.1918177143616812}, {"id": "CDR2", "name": "CDR2", "cluster": "paris.infomap.2021:1738", "cluster_id": 758, "x": -0.2219108787403584, "y": -0.28080484227784364}, {"id": "IGHV4-38-2", "name": "IGHV4-38-2", "cluster": "paris.infomap.2021:1738", "cluster_id": 758, "x": -0.17688038749235876, "y": 0.05757967471761714}, {"id": "GP6", "name": "GP6", "cluster": "paris.infomap.2021:1738", "cluster_id": 758, "x": 0.5218215875283999, "y": -0.47805883484455314}, {"id": "CDR1", "name": "CDR1", "cluster": "paris.infomap.2021:1738", "cluster_id": 758, "x": -0.09731367289058743, "y": -0.344546961598496}, {"id": "CCRL2", "name": "CCRL2", "cluster": "paris.infomap.2021:1738", "cluster_id": 758, "x": 0.2935865738479963, "y": 0.16122785015906674}, {"id": "FCRLA", "name": "FCRLA", "cluster": "paris.infomap.2021:1738", "cluster_id": 758, "x": 0.0028594788230986473, "y": 0.033798411636310526}, {"id": "PRDM1", "name": "PRDM1", "cluster": "paris.infomap.2021:1738", "cluster_id": 758, "x": 0.03563269543475595, "y": 0.23582620757720657}, {"id": "CD40", "name": "CD40", "cluster": "paris.infomap.2021:1738", "cluster_id": 758, "x": 0.13581433913676697, "y": -0.0013781491684932627}, {"id": "TNFSF13B", "name": "TNFSF13B", "cluster": "paris.infomap.2021:1738", "cluster_id": 758, "x": 0.22044715032964615, "y": -0.05313964886070971}, {"id": "CXCR5", "name": "CXCR5", "cluster": "paris.infomap.2021:1738", "cluster_id": 758, "x": 0.19464912653827413, "y": 0.22850441727868293}, {"id": "FCRL3", "name": "FCRL3", "cluster": "paris.infomap.2021:1738", "cluster_id": 758, "x": -0.06746275214359994, "y": 0.3292847298096195}, {"id": "AICDA", "name": "AICDA", "cluster": "paris.infomap.2021:1738", "cluster_id": 758, "x": 0.02821272864190621, "y": 0.10274917214841375}, {"id": "CD5", "name": "CD5", "cluster": "paris.infomap.2021:1738", "cluster_id": 758, "x": 0.18716837632525085, "y": 0.0707129645021751}, {"id": "CSF2RA", "name": "CSF2RA", "cluster": "paris.infomap.2021:1738", "cluster_id": 758, "x": 0.5931402501243884, "y": 0.07567273851887572}, {"id": "IGLL5", "name": "IGLL5", "cluster": "paris.infomap.2021:1738", "cluster_id": 758, "x": -0.27792234791005865, "y": -0.04641133965149406}, {"id": "IGHV3-11", "name": "IGHV3-11", "cluster": "paris.infomap.2021:1738", "cluster_id": 758, "x": -0.3681686026526896, "y": -0.1924725539104257}, {"id": "IGHV3-15", "name": "IGHV3-15", "cluster": "paris.infomap.2021:1738", "cluster_id": 758, "x": -0.4524939576016081, "y": -0.39880789634985614}, {"id": "IGHV3-43D", "name": "IGHV3-43D", "cluster": "paris.infomap.2021:1738", "cluster_id": 758, "x": -0.6954974010772345, "y": -0.22804992581730357}, {"id": "ZNF77", "name": "ZNF77", "cluster": "paris.infomap.2021:1738", "cluster_id": 758, "x": -0.5944291147251314, "y": -0.5984727565260127}, {"id": "LIME1", "name": "LIME1", "cluster": "paris.infomap.2021:1738", "cluster_id": 758, "x": -0.7512553503989163, "y": -0.03513643200557894}]}