{"edges": [["HP:0030880", "SLC12A3"], ["SLC12A3", "YEATS4"]], "nodes": [{"id": "HP:0030880", "name": "HP:0030880", "cluster": "paris.cesna.2021:22332", "cluster_id": 2910, "x": 1.0, "y": 0.1882377555570674}, {"id": "SLC12A3", "name": "SLC12A3", "cluster": "paris.cesna.2021:22332", "cluster_id": 2910, "x": -0.002246493229970637, "y": -0.00042287487092405196}, {"id": "YEATS4", "name": "YEATS4", "cluster": "paris.cesna.2021:22332", "cluster_id": 2910, "x": -0.9977535067700294, "y": -0.18781488068614371}]}