{"edges": [{"source": "HP:0000590", "target": "TRNL2"}, {"source": "HP:0001716", "target": "TRNC"}, {"source": "HP:0001716", "target": "TRNV"}, {"source": "HP:0002401", "target": "TRNC"}, {"source": "HP:0002401", "target": "TRNV"}, {"source": "HP:0002572", "target": "TRNC"}, {"source": "HP:0002572", "target": "ND3"}, {"source": "HP:0002572", "target": "TRNV"}, {"source": "HP:0002883", "target": "ND3"}, {"source": "HP:0002883", "target": "TRNV"}, {"source": "HP:0003200", "target": "TRNC"}, {"source": "HP:0003200", "target": "ND3"}, {"source": "HP:0003200", "target": "TRNL2"}, {"source": "HP:0003200", "target": "TRNV"}, {"source": "HP:0003481", "target": "ND3"}, {"source": "HP:0003481", "target": "TRNV"}, {"source": "HP:0003737", "target": "TRNC"}, {"source": "HP:0003737", "target": "ND3"}, {"source": "HP:0003737", "target": "TRNV"}, {"source": "HP:0004885", "target": "ND3"}, {"source": "HP:0004885", "target": "TRNV"}, {"source": "HP:0031546", "target": "ND3"}, {"source": "HP:0031546", "target": "TRNV"}, {"source": "HP:0008316", "target": "ND3"}, {"source": "HP:0008316", "target": "TRNL2"}], "nodes": [{"id": "HP:0000590", "name": "HP:0000590", "cluster": "paris.walktrap.2021:996", "cluster_id": 272, "x": 1.0, "y": 0.36474513800367614}, {"id": "TRNL2", "name": "TRNL2", "cluster": "paris.walktrap.2021:996", "cluster_id": 272, "x": 0.639057989407365, "y": 0.19201246895199073}, {"id": "HP:0001716", "name": "HP:0001716", "cluster": "paris.walktrap.2021:996", "cluster_id": 272, "x": -0.4558290969758511, "y": 0.3267644888271792}, {"id": "TRNC", "name": "TRNC", "cluster": "paris.walktrap.2021:996", "cluster_id": 272, "x": -0.21253209873730694, "y": 0.3093251461444093}, {"id": "TRNV", "name": "TRNV", "cluster": "paris.walktrap.2021:996", "cluster_id": 272, "x": -0.17595258686769424, "y": -0.058621279124551645}, {"id": "HP:0002401", "name": "HP:0002401", "cluster": "paris.walktrap.2021:996", "cluster_id": 272, "x": -0.07157201526050985, "y": 0.4101578178843097}, {"id": "HP:0002572", "name": "HP:0002572", "cluster": "paris.walktrap.2021:996", "cluster_id": 272, "x": -0.2227227321103554, "y": 0.10812824786552107}, {"id": "ND3", "name": "ND3", "cluster": "paris.walktrap.2021:996", "cluster_id": 272, "x": -0.04558546539581187, "y": -0.17935063202870485}, {"id": "HP:0002883", "name": "HP:0002883", "cluster": "paris.walktrap.2021:996", "cluster_id": 272, "x": 0.11873992880310728, "y": -0.3575864119485374}, {"id": "HP:0003200", "name": "HP:0003200", "cluster": "paris.walktrap.2021:996", "cluster_id": 272, "x": 0.161349559346519, "y": 0.1286829466689213}, {"id": "HP:0003481", "name": "HP:0003481", "cluster": "paris.walktrap.2021:996", "cluster_id": 272, "x": -0.2821202024575223, "y": -0.42721568703205703}, {"id": "HP:0003737", "name": "HP:0003737", "cluster": "paris.walktrap.2021:996", "cluster_id": 272, "x": -0.3904904087627485, "y": 0.020671742871698817}, {"id": "HP:0004885", "name": "HP:0004885", "cluster": "paris.walktrap.2021:996", "cluster_id": 272, "x": -0.4198926367616249, "y": -0.2798417166654729}, {"id": "HP:0031546", "name": "HP:0031546", "cluster": "paris.walktrap.2021:996", "cluster_id": 272, "x": -0.08432034549093843, "y": -0.46636215118613633}, {"id": "HP:0008316", "name": "HP:0008316", "cluster": "paris.walktrap.2021:996", "cluster_id": 272, "x": 0.4418701112633731, "y": -0.09151011923224625}]}