{"edges": [{"source": "COL5A1", "target": "HP:0000268"}, {"source": "DLX3", "target": "HP:0000268"}, {"source": "FBN1", "target": "HP:0000268"}, {"source": "FBN2", "target": "HP:0000268"}, {"source": "FGFR2", "target": "HP:0000268"}, {"source": "HP:0000268", "target": "IDUA"}, {"source": "HP:0000268", "target": "SMAD3"}, {"source": "HP:0000268", "target": "PRPS1"}, {"source": "HP:0000268", "target": "TWIST1"}, {"source": "IDUA", "target": "SMAD3"}, {"source": "FGFR2", "target": "TWIST1"}, {"source": "FBN1", "target": "FGFR2"}, {"source": "FGFR2", "target": "SMAD3"}, {"source": "COL5A1", "target": "FGFR2"}, {"source": "DLX3", "target": "FGFR2"}, {"source": "FBN2", "target": "TWIST1"}, {"source": "FBN1", "target": "FBN2"}, {"source": "FBN2", "target": "SMAD3"}, {"source": "COL5A1", "target": "FBN2"}, {"source": "COL5A1", "target": "TWIST1"}, {"source": "COL5A1", "target": "FBN1"}, {"source": "COL5A1", "target": "SMAD3"}, {"source": "FBN1", "target": "TWIST1"}, {"source": "FBN1", "target": "SMAD3"}, {"source": "SMAD3", "target": "TWIST1"}, {"source": "DLX3", "target": "TWIST1"}], "nodes": [{"id": "COL5A1", "name": "COL5A1", "cluster": "paris.cesna.2021:8858", "cluster_id": 1719, "x": -0.10474974379697712, "y": 0.42063497481434237}, {"id": "HP:0000268", "name": "HP:0000268", "cluster": "paris.cesna.2021:8858", "cluster_id": 1719, "x": 0.1733583207194649, "y": -0.053478654297510066}, {"id": "DLX3", "name": "DLX3", "cluster": "paris.cesna.2021:8858", "cluster_id": 1719, "x": -0.4357747575646874, "y": -0.459393232982832}, {"id": "FBN1", "name": "FBN1", "cluster": "paris.cesna.2021:8858", "cluster_id": 1719, "x": -0.3500267117412068, "y": 0.400545688102569}, {"id": "FBN2", "name": "FBN2", "cluster": "paris.cesna.2021:8858", "cluster_id": 1719, "x": 0.18256536084651953, "y": 0.4300257166551198}, {"id": "FGFR2", "name": "FGFR2", "cluster": "paris.cesna.2021:8858", "cluster_id": 1719, "x": -0.5108054962578059, "y": -0.014943849627752028}, {"id": "IDUA", "name": "IDUA", "cluster": "paris.cesna.2021:8858", "cluster_id": 1719, "x": 0.3547387934555964, "y": -0.6184387839109163}, {"id": "SMAD3", "name": "SMAD3", "cluster": "paris.cesna.2021:8858", "cluster_id": 1719, "x": -0.043627856714088795, "y": -0.07199585818265608}, {"id": "PRPS1", "name": "PRPS1", "cluster": "paris.cesna.2021:8858", "cluster_id": 1719, "x": 1.0, "y": -0.1262263600766977}, {"id": "TWIST1", "name": "TWIST1", "cluster": "paris.cesna.2021:8858", "cluster_id": 1719, "x": -0.26567790894681587, "y": 0.09327035950633382}]}