{"edges": [{"source": "HP:0001249", "target": "HP:0006887"}, {"source": "HP:0001249", "target": "HP:0010864"}, {"source": "AHSG", "target": "HP:0001249"}, {"source": "HP:0001249", "target": "OFD1"}, {"source": "AIFM1", "target": "HP:0001249"}, {"source": "HP:0001249", "target": "SNAP29"}, {"source": "HP:0001249", "target": "RAB3GAP2"}, {"source": "HP:0001249", "target": "WDR81"}, {"source": "HP:0001249", "target": "KCNH1"}, {"source": "HP:0001249", "target": "MTRR"}, {"source": "HP:0001249", "target": "TONSL"}, {"source": "HP:0001249", "target": "PEX1"}, {"source": "HP:0001249", "target": "PTS"}, {"source": "HP:0001249", "target": "SRD5A3"}, {"source": "HP:0001249", "target": "SNRPN"}, {"source": "ACOX1", "target": "HP:0006887"}, {"source": "AHSG", "target": "HP:0006887"}, {"source": "HP:0006887", "target": "OFD1"}, {"source": "HP:0006887", "target": "UROC1"}, {"source": "HP:0006887", "target": "SUCLA2"}, {"source": "AIFM1", "target": "HP:0006887"}, {"source": "AP4M1", "target": "HP:0006887"}, {"source": "HP:0006887", "target": "SNAP29"}, {"source": "HP:0006887", "target": "RAB3GAP2"}, {"source": "CTSD", "target": "HP:0006887"}, {"source": "HP:0006887", "target": "WDR81"}, {"source": "GCH1", "target": "HP:0006887"}, {"source": "HP:0006887", "target": "KCNH1"}, {"source": "HP:0006887", "target": "MGAT2"}, {"source": "HP:0006887", "target": "MTRR"}, {"source": "HP:0006887", "target": "NDP"}, {"source": "HP:0006887", "target": "TONSL"}, {"source": "HP:0006887", "target": "PEX1"}, {"source": "HP:0006887", "target": "NDE1"}, {"source": "HP:0006887", "target": "PTS"}, {"source": "HP:0006887", "target": "SRD5A3"}, {"source": "HP:0006887", "target": "SLC35C1"}, {"source": "HP:0006887", "target": "L2HGDH"}, {"source": "HP:0006887", "target": "SLC16A2"}, {"source": "HP:0006887", "target": "SNRPN"}, {"source": "ACOX1", "target": "HP:0010864"}, {"source": "AHSG", "target": "HP:0010864"}, {"source": "HP:0010864", "target": "OFD1"}, {"source": "HP:0010864", "target": "UROC1"}, {"source": "AP4M1", "target": "HP:0010864"}, {"source": "HP:0010864", "target": "SNAP29"}, {"source": "HP:0010864", "target": "RAB3GAP2"}, {"source": "CTSD", "target": "HP:0010864"}, {"source": "HP:0010864", "target": "WDR81"}, {"source": "HP:0010864", "target": "KCNH1"}, {"source": "HP:0010864", "target": "MGAT2"}, {"source": "HP:0010864", "target": "PEX1"}, {"source": "HP:0010864", "target": "NDE1"}, {"source": "HP:0010864", "target": "SRD5A3"}, {"source": "HP:0010864", "target": "SLC35C1"}, {"source": "HP:0010864", "target": "L2HGDH"}, {"source": "HP:0010864", "target": "SLC16A2"}, {"source": "HP:0010864", "target": "SNRPN"}, {"source": "AP4M1", "target": "RAB3GAP2"}, {"source": "AP4M1", "target": "SLC16A2"}, {"source": "CTSD", "target": "SNAP29"}, {"source": "AHSG", "target": "CTSD"}, {"source": "AIFM1", "target": "CTSD"}, {"source": "ACOX1", "target": "PEX1"}, {"source": "ACOX1", "target": "AIFM1"}, {"source": "ACOX1", "target": "SUCLA2"}, {"source": "PEX1", "target": "SNAP29"}, {"source": "GCH1", "target": "PTS"}, {"source": "SLC35C1", "target": "SRD5A3"}, {"source": "MGAT2", "target": "SLC35C1"}, {"source": "SLC16A2", "target": "SLC35C1"}, {"source": "RAB3GAP2", "target": "SLC16A2"}, {"source": "SNAP29", "target": "SRD5A3"}, {"source": "RAB3GAP2", "target": "SNAP29"}, {"source": "NDE1", "target": "SNAP29"}, {"source": "AIFM1", "target": "L2HGDH"}, {"source": "AIFM1", "target": "GCH1"}, {"source": "AIFM1", "target": "TONSL"}, {"source": "GCH1", "target": "MTRR"}, {"source": "NDE1", "target": "OFD1"}, {"source": "NDE1", "target": "RAB3GAP2"}, {"source": "AHSG", "target": "UROC1"}, {"source": "L2HGDH", "target": "SUCLA2"}, {"source": "SNRPN", "target": "UROC1"}, {"source": "RAB3GAP2", "target": "WDR81"}], "nodes": [{"id": "HP:0001249", "name": "HP:0001249", "cluster": "paris.cesna.2021:24848", "cluster_id": 3159, "x": -0.2360124312210466, "y": -0.009052948151940254}, {"id": "HP:0006887", "name": "HP:0006887", "cluster": "paris.cesna.2021:24848", "cluster_id": 3159, "x": -0.007129286787801207, "y": -0.01186556391047078}, {"id": "HP:0010864", "name": "HP:0010864", "cluster": "paris.cesna.2021:24848", "cluster_id": 3159, "x": 0.13732040550972074, "y": 0.16652957634738902}, {"id": "AHSG", "name": "AHSG", "cluster": "paris.cesna.2021:24848", "cluster_id": 3159, "x": -0.44795720602489036, "y": -0.2043125050482163}, {"id": "OFD1", "name": "OFD1", "cluster": "paris.cesna.2021:24848", "cluster_id": 3159, "x": 0.282984531758631, "y": 0.5396939856920578}, {"id": "AIFM1", "name": "AIFM1", "cluster": "paris.cesna.2021:24848", "cluster_id": 3159, "x": -0.13843930903619286, "y": -0.7290215229272712}, {"id": "SNAP29", "name": "SNAP29", "cluster": "paris.cesna.2021:24848", "cluster_id": 3159, "x": 0.335028566321044, "y": 0.16128210094907244}, {"id": "RAB3GAP2", "name": "RAB3GAP2", "cluster": "paris.cesna.2021:24848", "cluster_id": 3159, "x": 0.10587426683042109, "y": 0.5778284521631415}, {"id": "WDR81", "name": "WDR81", "cluster": "paris.cesna.2021:24848", "cluster_id": 3159, "x": -0.23147802878824966, "y": 0.654647026971762}, {"id": "KCNH1", "name": "KCNH1", "cluster": "paris.cesna.2021:24848", "cluster_id": 3159, "x": -0.48719421823275294, "y": 0.5373440614395009}, {"id": "MTRR", "name": "MTRR", "cluster": "paris.cesna.2021:24848", "cluster_id": 3159, "x": -0.4562185688592177, "y": -0.799806209913577}, {"id": "TONSL", "name": "TONSL", "cluster": "paris.cesna.2021:24848", "cluster_id": 3159, "x": -0.6156734054676157, "y": -0.5305411985361594}, {"id": "PEX1", "name": "PEX1", "cluster": "paris.cesna.2021:24848", "cluster_id": 3159, "x": 0.15451553484558828, "y": -0.27297876746055977}, {"id": "PTS", "name": "PTS", "cluster": "paris.cesna.2021:24848", "cluster_id": 3159, "x": -0.9227535662527342, "y": -0.33712289867920797}, {"id": "SRD5A3", "name": "SRD5A3", "cluster": "paris.cesna.2021:24848", "cluster_id": 3159, "x": 0.546401554595636, "y": -0.09880124261033554}, {"id": "SNRPN", "name": "SNRPN", "cluster": "paris.cesna.2021:24848", "cluster_id": 3159, "x": -0.6363936604530651, "y": 0.3284338335140455}, {"id": "ACOX1", "name": "ACOX1", "cluster": "paris.cesna.2021:24848", "cluster_id": 3159, "x": 0.2756312250962096, "y": -0.7069688413094826}, {"id": "UROC1", "name": "UROC1", "cluster": "paris.cesna.2021:24848", "cluster_id": 3159, "x": -0.7429354022815469, "y": 0.10722113457611886}, {"id": "SUCLA2", "name": "SUCLA2", "cluster": "paris.cesna.2021:24848", "cluster_id": 3159, "x": 0.6461802365353851, "y": -0.9301982419871371}, {"id": "AP4M1", "name": "AP4M1", "cluster": "paris.cesna.2021:24848", "cluster_id": 3159, "x": 0.5349270637561424, "y": 0.7871695222866558}, {"id": "CTSD", "name": "CTSD", "cluster": "paris.cesna.2021:24848", "cluster_id": 3159, "x": 0.10177848622425148, "y": -0.45478633343712765}, {"id": "GCH1", "name": "GCH1", "cluster": "paris.cesna.2021:24848", "cluster_id": 3159, "x": -0.742157100207505, "y": -0.826224281499232}, {"id": "MGAT2", "name": "MGAT2", "cluster": "paris.cesna.2021:24848", "cluster_id": 3159, "x": 0.9308893244985209, "y": 0.27220850662777707}, {"id": "NDP", "name": "NDP", "cluster": "paris.cesna.2021:24848", "cluster_id": 3159, "x": -0.6691716258563519, "y": 1.0}, {"id": "NDE1", "name": "NDE1", "cluster": "paris.cesna.2021:24848", "cluster_id": 3159, "x": 0.21626363099942322, "y": 0.8185413658279512}, {"id": "SLC35C1", "name": "SLC35C1", "cluster": "paris.cesna.2021:24848", "cluster_id": 3159, "x": 0.8616121376101047, "y": 0.03791362510509206}, {"id": "L2HGDH", "name": "L2HGDH", "cluster": "paris.cesna.2021:24848", "cluster_id": 3159, "x": 0.517636136747077, "y": -0.5825465113493388}, {"id": "SLC16A2", "name": "SLC16A2", "cluster": "paris.cesna.2021:24848", "cluster_id": 3159, "x": 0.6864707081408171, "y": 0.5054138753194917}]}