{"edges": [{"source": "HP:0003396", "target": "SH2B1"}, {"source": "HP:0007166", "target": "SH2B1"}, {"source": "FAM184B", "target": "TBC1D22B"}, {"source": "PRKD1", "target": "TBC1D22B"}, {"source": "FAM217B", "target": "TBC1D22B"}, {"source": "PPP1R3D", "target": "TBC1D22B"}, {"source": "TBC1D22B", "target": "VSTM2L"}, {"source": "TBC1D22B", "target": "ZFAT"}, {"source": "FTO", "target": "TBC1D22B"}, {"source": "ADCY8", "target": "MAP2K5"}, {"source": "MAP2K5", "target": "PRKD1"}, {"source": "MAP2K5", "target": "TUB"}, {"source": "GPRC5B", "target": "MAP2K5"}, {"source": "CADM2", "target": "MAP2K5"}, {"source": "MAP2K5", "target": "SLC39A8"}, {"source": "DNAJC27", "target": "MAP2K5"}, {"source": "MAP2K5", "target": "TMEM18"}, {"source": "IQCK", "target": "MAP2K5"}, {"source": "GALNT10", "target": "MAP2K5"}, {"source": "MAP2K5", "target": "SKOR1"}, {"source": "MAP2K5", "target": "THBD"}, {"source": "FAIM2", "target": "MAP2K5"}, {"source": "ADCY3", "target": "MAP2K5"}, {"source": "MAP2K5", "target": "SH2B1"}, {"source": "MAP2K5", "target": "TNNI3K"}, {"source": "BDNF", "target": "MAP2K5"}, {"source": "HMGCR", "target": "MAP2K5"}, {"source": "GIPR", "target": "MAP2K5"}, {"source": "DCST2", "target": "MAP2K5"}, {"source": "FTO", "target": "MAP2K5"}, {"source": "LRP1B", "target": "MAP2K5"}, {"source": "ADCY3", "target": "PRKD1"}, {"source": "DNAJC27", "target": "PRKD1"}, {"source": "PRKD1", "target": "TMEM18"}, {"source": "ADCY8", "target": "PRKD1"}, {"source": "GPRC5B", "target": "PRKD1"}, {"source": "PRKD1", "target": "TUB"}, {"source": "PRKD1", "target": "SH2B1"}, {"source": "FAIM2", "target": "PRKD1"}, {"source": "PRKD1", "target": "TNNI3K"}, {"source": "IQCK", "target": "PRKD1"}, {"source": "HDAC9", "target": "PRKD1"}, {"source": "BDNF", "target": "PRKD1"}, {"source": "PRKD1", "target": "SLC39A8"}, {"source": "CADM2", "target": "PRKD1"}, {"source": "GIPR", "target": "PRKD1"}, {"source": "LRP1B", "target": "PRKD1"}, {"source": "PRKD1", "target": "SKOR1"}, {"source": "FTO", "target": "PRKD1"}, {"source": "ADCY8", "target": "OCEL1"}, {"source": "ADCY3", "target": "ADCY8"}, {"source": "ADCY8", "target": "DNAJC27"}, {"source": "ADCY8", "target": "TMEM18"}, {"source": "ADCY8", "target": "FAIM2"}, {"source": "ADCY8", "target": "TNNI3K"}, {"source": "ADCY8", "target": "SH2B1"}, {"source": "ADCY8", "target": "HMGCR"}, {"source": "ADCY8", "target": "BDNF"}, {"source": "ADCY8", "target": "GIPR"}, {"source": "ADCY8", "target": "FTO"}, {"source": "ADCY8", "target": "DCST2"}, {"source": "ADCY8", "target": "LRP1B"}, {"source": "ADCY8", "target": "TUB"}, {"source": "ADCY8", "target": "CADM2"}, {"source": "ADCY8", "target": "GPRC5B"}, {"source": "ADCY8", "target": "SLC39A8"}, {"source": "ADCY8", "target": "IQCK"}, {"source": "ADCY8", "target": "GALNT10"}, {"source": "ADCY8", "target": "KLHL32"}, {"source": "ADCY8", "target": "SKOR1"}, {"source": "ADCY3", "target": "OCEL1"}, {"source": "ADCY3", "target": "TUB"}, {"source": "ADCY3", "target": "GPRC5B"}, {"source": "ADCY3", "target": "CADM2"}, {"source": "ADCY3", "target": "SLC39A8"}, {"source": "ADCY3", "target": "DNAJC27"}, {"source": "ADCY3", "target": "IQCK"}, {"source": "ADCY3", "target": "TMEM18"}, {"source": "ADCY3", "target": "GALNT10"}, {"source": "ADCY3", "target": "KLHL32"}, {"source": "ADCY3", "target": "SKOR1"}, {"source": "ADCY3", "target": "FAIM2"}, {"source": "ADCY3", "target": "TNNI3K"}, {"source": "ADCY3", "target": "SH2B1"}, {"source": "ADCY3", "target": "HMGCR"}, {"source": "ADCY3", "target": "BDNF"}, {"source": "ADCY3", "target": "GIPR"}, {"source": "ADCY3", "target": "SPRYD7"}, {"source": "ADCY3", "target": "FTO"}, {"source": "ADCY3", "target": "DCST2"}, {"source": "ADCY3", "target": "LRP1B"}, {"source": "BDNF", "target": "DNAJC27"}, {"source": "BDNF", "target": "TMEM18"}, {"source": "BDNF", "target": "HMGCR"}, {"source": "BDNF", "target": "GPRC5B"}, {"source": "BDNF", "target": "TUB"}, {"source": "BDNF", "target": "SH2B1"}, {"source": "BDNF", "target": "FAIM2"}, {"source": "BDNF", "target": "TNNI3K"}, {"source": "BDNF", "target": "SKOR1"}, {"source": "BDNF", "target": "SLC39A8"}, {"source": "BDNF", "target": "CADM2"}, {"source": "BDNF", "target": "HDAC9"}, {"source": "BDNF", "target": "GIPR"}, {"source": "BDNF", "target": "FTO"}, {"source": "FAIM2", "target": "NFE2L3"}, {"source": "DNAJC27", "target": "FAIM2"}, {"source": "FAIM2", "target": "TMEM18"}, {"source": "FAIM2", "target": "HMGCR"}, {"source": "FAIM2", "target": "GPRC5B"}, {"source": "FAIM2", "target": "TUB"}, {"source": "FAIM2", "target": "SH2B1"}, {"source": "FAIM2", "target": "LRP1B"}, {"source": "FAIM2", "target": "FTO"}, {"source": "FAIM2", "target": "VSTM2L"}, {"source": "FAIM2", "target": "GIPR"}, {"source": "FAIM2", "target": "TNNI3K"}, {"source": "FAIM2", "target": "SKOR1"}, {"source": "FAIM2", "target": "KLHL32"}, {"source": "FAIM2", "target": "IQCK"}, {"source": "FAIM2", "target": "SLC39A8"}, {"source": "CADM2", "target": "FAIM2"}, {"source": "CYP24A1", "target": "OCEL1"}, {"source": "CYP24A1", "target": "THBD"}, {"source": "CYP24A1", "target": "HMGCR"}, {"source": "CYP24A1", "target": "FAM217B"}, {"source": "CYP24A1", "target": "PPP1R3D"}, {"source": "DNAJC27", "target": "HMGCR"}, {"source": "HMGCR", "target": "TMEM18"}, {"source": "HMGCR", "target": "SLC39A8"}, {"source": "CADM2", "target": "HMGCR"}, {"source": "GPRC5B", "target": "HMGCR"}, {"source": "HMGCR", "target": "SH2B1"}, {"source": "HMGCR", "target": "TUB"}, {"source": "HMGCR", "target": "TNNI3K"}, {"source": "HMGCR", "target": "THBD"}, {"source": "HMGCR", "target": "LRP1B"}, {"source": "HMGCR", "target": "SKOR1"}, {"source": "GIPR", "target": "HMGCR"}, {"source": "HMGCR", "target": "IQCK"}, {"source": "GALNT10", "target": "NFE2L3"}, {"source": "DNAJC27", "target": "GALNT10"}, {"source": "GALNT10", "target": "TMEM18"}, {"source": "GALNT10", "target": "SLC39A8"}, {"source": "GALNT10", "target": "GPRC5B"}, {"source": "CADM2", "target": "GALNT10"}, {"source": "GALNT10", "target": "TNNI3K"}, {"source": "GALNT10", "target": "SH2B1"}, {"source": "GALNT10", "target": "IRX4"}, {"source": "GALNT10", "target": "KLHL32"}, {"source": "GALNT10", "target": "LRP1B"}, {"source": "FTO", "target": "GALNT10"}, {"source": "DCST2", "target": "GALNT10"}, {"source": "GALNT10", "target": "SPRYD7"}, {"source": "GALNT10", "target": "ZDHHC1"}, {"source": "OCEL1", "target": "THBD"}, {"source": "LRRC25", "target": "THBD"}, {"source": "FAM217B", "target": "THBD"}, {"source": "CADM2", "target": "DNAJC27"}, {"source": "CADM2", "target": "TMEM18"}, {"source": "CADM2", "target": "GPRC5B"}, {"source": "CADM2", "target": "TUB"}, {"source": "CADM2", "target": "SH2B1"}, {"source": "CADM2", "target": "TNNI3K"}, {"source": "CADM2", "target": "IQCK"}, {"source": "CADM2", "target": "SKOR1"}, {"source": "CADM2", "target": "KLHL32"}, {"source": "CADM2", "target": "VSTM2L"}, {"source": "CADM2", "target": "ZFAT"}, {"source": "CADM2", "target": "LRP1B"}, {"source": "CADM2", "target": "SLC39A8"}, {"source": "CADM2", "target": "FTO"}, {"source": "CADM2", "target": "GIPR"}, {"source": "HDAC9", "target": "SSBP4"}, {"source": "HDAC9", "target": "SKOR1"}, {"source": "HDAC9", "target": "VSTM2L"}, {"source": "HDAC9", "target": "ZFAT"}, {"source": "FTO", "target": "HDAC9"}, {"source": "DNAJC27", "target": "TUB"}, {"source": "TMEM18", "target": "TUB"}, {"source": "GPRC5B", "target": "TUB"}, {"source": "GIPR", "target": "TUB"}, {"source": "FTO", "target": "TUB"}, {"source": "LRP1B", "target": "TUB"}, {"source": "TNNI3K", "target": "TUB"}, {"source": "SH2B1", "target": "TUB"}, {"source": "IQCK", "target": "TUB"}, {"source": "SKOR1", "target": "TUB"}, {"source": "SLC39A8", "target": "TUB"}, {"source": "NFE2L3", "target": "SPRYD7"}, {"source": "SPRYD7", "target": "TMEM18"}, {"source": "SPRYD7", "target": "ZDHHC1"}, {"source": "IRX4", "target": "SPRYD7"}, {"source": "KLHL32", "target": "SPRYD7"}, {"source": "DCST2", "target": "SPRYD7"}, {"source": "NFE2L3", "target": "TNNI3K"}, {"source": "DNAJC27", "target": "TNNI3K"}, {"source": "TMEM18", "target": "TNNI3K"}, {"source": "GPRC5B", "target": "TNNI3K"}, {"source": "SH2B1", "target": "TNNI3K"}, {"source": "SKOR1", "target": "TNNI3K"}, {"source": "KLHL32", "target": "TNNI3K"}, {"source": "IQCK", "target": "TNNI3K"}, {"source": "SLC39A8", "target": "TNNI3K"}, {"source": "LRP1B", "target": "TNNI3K"}, {"source": "FTO", "target": "TNNI3K"}, {"source": "GIPR", "target": "TNNI3K"}, {"source": "FTO", "target": "NFE2L3"}, {"source": "DNAJC27", "target": "FTO"}, {"source": "FAM184B", "target": "FTO"}, {"source": "FTO", "target": "SSBP4"}, {"source": "FTO", "target": "TMEM18"}, {"source": "FTO", "target": "GPRC5B"}, {"source": "FTO", "target": "SH2B1"}, {"source": "FTO", "target": "SKOR1"}, {"source": "DCST2", "target": "FTO"}, {"source": "FTO", "target": "KLHL32"}, {"source": "FTO", "target": "VSTM2L"}, {"source": "FTO", "target": "ZFAT"}, {"source": "FTO", "target": "LRP1B"}, {"source": "FTO", "target": "SLC39A8"}, {"source": "FTO", "target": "GIPR"}, {"source": "FTO", "target": "IRX4"}, {"source": "OCEL1", "target": "PPP1R3D"}, {"source": "GPRC5B", "target": "PPP1R3D"}, {"source": "FAM217B", "target": "PPP1R3D"}, {"source": "PPP1R3D", "target": "ZFAT"}, {"source": "KLHL32", "target": "NFE2L3"}, {"source": "DNAJC27", "target": "KLHL32"}, {"source": "KLHL32", "target": "TMEM18"}, {"source": "KLHL32", "target": "ZDHHC1"}, {"source": "DCST2", "target": "KLHL32"}, {"source": "IRX4", "target": "KLHL32"}, {"source": "DNAJC27", "target": "LRP1B"}, {"source": "LRP1B", "target": "TMEM18"}, {"source": "GPRC5B", "target": "LRP1B"}, {"source": "LRP1B", "target": "SH2B1"}, {"source": "IQCK", "target": "LRP1B"}, {"source": "LRP1B", "target": "SKOR1"}, {"source": "GIPR", "target": "LRP1B"}, {"source": "LRP1B", "target": "SLC39A8"}, {"source": "FAM184B", "target": "VSTM2L"}, {"source": "NFE2L3", "target": "TMEM18"}, {"source": "NFE2L3", "target": "ZDHHC1"}, {"source": "DCST2", "target": "NFE2L3"}, {"source": "DNAJC27", "target": "NFE2L3"}, {"source": "DNAJC27", "target": "GPRC5B"}, {"source": "GPRC5B", "target": "TMEM18"}, {"source": "GPRC5B", "target": "SLC39A8"}, {"source": "GPRC5B", "target": "SH2B1"}, {"source": "GPRC5B", "target": "SKOR1"}, {"source": "GIPR", "target": "GPRC5B"}, {"source": "GPRC5B", "target": "IQCK"}, {"source": "FAM217B", "target": "GPRC5B"}, {"source": "DCST2", "target": "SH2B1"}, {"source": "DCST2", "target": "ZDHHC1"}, {"source": "IRX4", "target": "ZDHHC1"}, {"source": "DNAJC27", "target": "SLC39A8"}, {"source": "SLC39A8", "target": "TMEM18"}, {"source": "SH2B1", "target": "SLC39A8"}, {"source": "IQCK", "target": "SLC39A8"}, {"source": "SKOR1", "target": "SLC39A8"}, {"source": "GIPR", "target": "SLC39A8"}, {"source": "DNAJC27", "target": "GIPR"}, {"source": "GIPR", "target": "TMEM18"}, {"source": "GIPR", "target": "SH2B1"}, {"source": "GIPR", "target": "IQCK"}, {"source": "GIPR", "target": "SKOR1"}, {"source": "DNAJC27", "target": "TMEM18"}, {"source": "TMEM18", "target": "ZDHHC1"}, {"source": "IQCK", "target": "TMEM18"}, {"source": "SKOR1", "target": "TMEM18"}, {"source": "SH2B1", "target": "TMEM18"}, {"source": "DNAJC27", "target": "IQCK"}, {"source": "IQCK", "target": "SH2B1"}, {"source": "IQCK", "target": "SKOR1"}, {"source": "DNAJC27", "target": "SH2B1"}, {"source": "SH2B1", "target": "SKOR1"}, {"source": "DNAJC27", "target": "SKOR1"}, {"source": "FAM184B", "target": "ZFAT"}, {"source": "FAM217B", "target": "ZFAT"}, {"source": "ASCL5", "target": "ZFAT"}, {"source": "LRRC25", "target": "OCEL1"}, {"source": "LRRC25", "target": "SSBP4"}, {"source": "FAM217B", "target": "LRRC25"}, {"source": "OCEL1", "target": "SSBP4"}, {"source": "C12orf75", "target": "FAM184B"}, {"source": "ASCL5", "target": "C12orf75"}, {"source": "FAM217B", "target": "OCEL1"}], "nodes": [{"id": "HP:0003396", "name": "HP:0003396", "cluster": "paris.walktrap.2021:1107", "cluster_id": 326, "x": 0.8222908153185606, "y": 0.04215990837341031}, {"id": "SH2B1", "name": "SH2B1", "cluster": "paris.walktrap.2021:1107", "cluster_id": 326, "x": 0.32754626354119226, "y": -0.04987857451092757}, {"id": "HP:0007166", "name": "HP:0007166", "cluster": "paris.walktrap.2021:1107", "cluster_id": 326, "x": 0.8154041254415714, "y": -0.18742839952443927}, {"id": "FAM184B", "name": "FAM184B", "cluster": "paris.walktrap.2021:1107", "cluster_id": 326, "x": -0.5663867627822832, "y": -0.14160399002856355}, {"id": "TBC1D22B", "name": "TBC1D22B", "cluster": "paris.walktrap.2021:1107", "cluster_id": 326, "x": -0.3677707691338217, "y": 0.0630549116466992}, {"id": "PRKD1", "name": "PRKD1", "cluster": "paris.walktrap.2021:1107", "cluster_id": 326, "x": 0.03178348689274076, "y": 0.03375819258415316}, {"id": "FAM217B", "name": "FAM217B", "cluster": "paris.walktrap.2021:1107", "cluster_id": 326, "x": -0.33177610659764595, "y": 0.3837889258559184}, {"id": "PPP1R3D", "name": "PPP1R3D", "cluster": "paris.walktrap.2021:1107", "cluster_id": 326, "x": -0.38130703123515025, "y": 0.2904627898831313}, {"id": "VSTM2L", "name": "VSTM2L", "cluster": "paris.walktrap.2021:1107", "cluster_id": 326, "x": -0.28739555707017184, "y": -0.12437073045063654}, {"id": "ZFAT", "name": "ZFAT", "cluster": "paris.walktrap.2021:1107", "cluster_id": 326, "x": -0.46417887581445944, "y": 0.055823095020408914}, {"id": "FTO", "name": "FTO", "cluster": "paris.walktrap.2021:1107", "cluster_id": 326, "x": -0.040118654569636404, "y": -0.08070544104830078}, {"id": "ADCY8", "name": "ADCY8", "cluster": "paris.walktrap.2021:1107", "cluster_id": 326, "x": 0.10423152974031781, "y": -0.014709310970146439}, {"id": "MAP2K5", "name": "MAP2K5", "cluster": "paris.walktrap.2021:1107", "cluster_id": 326, "x": 0.12445591368001678, "y": 0.048672662802703034}, {"id": "TUB", "name": "TUB", "cluster": "paris.walktrap.2021:1107", "cluster_id": 326, "x": 0.20761287991962463, "y": 0.05461321137972525}, {"id": "GPRC5B", "name": "GPRC5B", "cluster": "paris.walktrap.2021:1107", "cluster_id": 326, "x": 0.017995440789860994, "y": 0.09196518315198877}, {"id": "CADM2", "name": "CADM2", "cluster": "paris.walktrap.2021:1107", "cluster_id": 326, "x": 0.019558446355307246, "y": -0.03767433374875465}, {"id": "SLC39A8", "name": "SLC39A8", "cluster": "paris.walktrap.2021:1107", "cluster_id": 326, "x": 0.19092770315402383, "y": -0.010638601028460681}, {"id": "DNAJC27", "name": "DNAJC27", "cluster": "paris.walktrap.2021:1107", "cluster_id": 326, "x": 0.19672674542513452, "y": -0.10726177850566955}, {"id": "TMEM18", "name": "TMEM18", "cluster": "paris.walktrap.2021:1107", "cluster_id": 326, "x": 0.15235162591582854, "y": -0.14804479790387248}, {"id": "IQCK", "name": "IQCK", "cluster": "paris.walktrap.2021:1107", "cluster_id": 326, "x": 0.2975607210072562, "y": 0.055669857579162096}, {"id": "GALNT10", "name": "GALNT10", "cluster": "paris.walktrap.2021:1107", "cluster_id": 326, "x": 0.1595142734802454, "y": -0.24188544133709325}, {"id": "SKOR1", "name": "SKOR1", "cluster": "paris.walktrap.2021:1107", "cluster_id": 326, "x": 0.15527005533124957, "y": 0.10817614219142735}, {"id": "THBD", "name": "THBD", "cluster": "paris.walktrap.2021:1107", "cluster_id": 326, "x": -0.04623151542756452, "y": 0.4858451576030052}, {"id": "FAIM2", "name": "FAIM2", "cluster": "paris.walktrap.2021:1107", "cluster_id": 326, "x": 0.11533855687381897, "y": -0.0865078347151773}, {"id": "ADCY3", "name": "ADCY3", "cluster": "paris.walktrap.2021:1107", "cluster_id": 326, "x": 0.06922790075978986, "y": -0.08083826787511232}, {"id": "TNNI3K", "name": "TNNI3K", "cluster": "paris.walktrap.2021:1107", "cluster_id": 326, "x": 0.22901945232280757, "y": -0.08134494124632993}, {"id": "BDNF", "name": "BDNF", "cluster": "paris.walktrap.2021:1107", "cluster_id": 326, "x": 0.08414084151903597, "y": 0.10897295791911407}, {"id": "HMGCR", "name": "HMGCR", "cluster": "paris.walktrap.2021:1107", "cluster_id": 326, "x": 0.13910450513421255, "y": 0.18253739620480955}, {"id": "GIPR", "name": "GIPR", "cluster": "paris.walktrap.2021:1107", "cluster_id": 326, "x": 0.24123999030445917, "y": 0.09257856369034999}, {"id": "DCST2", "name": "DCST2", "cluster": "paris.walktrap.2021:1107", "cluster_id": 326, "x": 0.046020436808866506, "y": -0.29483742582233674}, {"id": "LRP1B", "name": "LRP1B", "cluster": "paris.walktrap.2021:1107", "cluster_id": 326, "x": 0.2534996058277586, "y": -0.014539885819103029}, {"id": "HDAC9", "name": "HDAC9", "cluster": "paris.walktrap.2021:1107", "cluster_id": 326, "x": -0.20683357464439225, "y": 0.11919813266168439}, {"id": "OCEL1", "name": "OCEL1", "cluster": "paris.walktrap.2021:1107", "cluster_id": 326, "x": -0.14088801577402585, "y": 0.3480508106184452}, {"id": "KLHL32", "name": "KLHL32", "cluster": "paris.walktrap.2021:1107", "cluster_id": 326, "x": 0.11508578769944827, "y": -0.31423737997605056}, {"id": "SPRYD7", "name": "SPRYD7", "cluster": "paris.walktrap.2021:1107", "cluster_id": 326, "x": 0.0661941332131499, "y": -0.45542299616106785}, {"id": "NFE2L3", "name": "NFE2L3", "cluster": "paris.walktrap.2021:1107", "cluster_id": 326, "x": 0.21248556997187004, "y": -0.358014910025066}, {"id": "CYP24A1", "name": "CYP24A1", "cluster": "paris.walktrap.2021:1107", "cluster_id": 326, "x": -0.1709109814636316, "y": 0.5345732242958683}, {"id": "IRX4", "name": "IRX4", "cluster": "paris.walktrap.2021:1107", "cluster_id": 326, "x": 0.19050579582988994, "y": -0.5253687779994809}, {"id": "ZDHHC1", "name": "ZDHHC1", "cluster": "paris.walktrap.2021:1107", "cluster_id": 326, "x": 0.11307997770237276, "y": -0.5414065775790705}, {"id": "LRRC25", "name": "LRRC25", "cluster": "paris.walktrap.2021:1107", "cluster_id": 326, "x": -0.3008252171482087, "y": 0.64507014419897}, {"id": "SSBP4", "name": "SSBP4", "cluster": "paris.walktrap.2021:1107", "cluster_id": 326, "x": -0.2575038699751759, "y": 0.375810536994862}, {"id": "ASCL5", "name": "ASCL5", "cluster": "paris.walktrap.2021:1107", "cluster_id": 326, "x": -0.9360456483242439, "y": -0.011627893966933462}, {"id": "C12orf75", "name": "C12orf75", "cluster": "paris.walktrap.2021:1107", "cluster_id": 326, "x": -0.9999999999999999, "y": -0.21243351441324113}]}