{"edges": [{"source": "HP:0000347", "target": "KCNJ5"}, {"source": "HP:0006696", "target": "KCNJ5"}], "nodes": [{"id": "HP:0000347", "type": "HPO", "name": "Micrognathia", "cluster": "paris.cesna.2021:22463", "cluster_id": 2920, "x": -0.2610265487974515, "y": 0.9999999999999999}, {"id": "KCNJ5", "type": "gene", "name": "Potassium inwardly rectifying channel subfamily J member 5", "cluster": "paris.cesna.2021:22463", "cluster_id": 2920, "x": 0.0006071552034955932, "y": -0.0023261636424044938}, {"id": "HP:0006696", "type": "HPO", "name": "Polymorphic and polytopic ventricular extrasystoles", "cluster": "paris.cesna.2021:22463", "cluster_id": 2920, "x": 0.26041939359395583, "y": -0.9976738363575951}], "hpoParentNodes": [{"id": "HP:0009118", "level": 1, "name": "Aplasia/Hypoplasia of the mandible", "type": "HPO Parent", "cluster": "paris.cesna.2021:22463", "cluster_id": 2920}, {"id": "HP:0006682", "level": 1, "name": "Premature ventricular contraction", "type": "HPO Parent", "cluster": "paris.cesna.2021:22463", "cluster_id": 2920}], "hpoParentEdges": [{"target": "HP:0000347", "source": "HP:0009118"}, {"target": "HP:0006682", "source": "HP:0006696"}]}